scrapper/__init__.py
scrapper/bootstrap.py
scrapper/css_scrapper.py
scrapper/html_scapper.py
html_scrapper-0.0.1.dist-info/METADATA
html_scrapper-0.0.1.dist-info/WHEEL
html_scrapper-0.0.1.dist-info/entry_points.txt
html_scrapper-0.0.1.dist-info/top_level.txt
html_scrapper-0.0.1.dist-info/RECORD
