Metadata-Version: 2.1
Name: html-scrapper
Version: 0.0.1
Summary: The package helps developers to scrap html content from a theme file
Home-page: https://github.com/dextrop/scrapper
Author: Dextrop
Author-email: scoder91@gmail.com
Classifier: License :: OSI Approved :: MIT License
Classifier: Programming Language :: Python :: 3
Classifier: Programming Language :: Python :: 3.7
Requires-Dist: cssutils
Requires-Dist: bs4
Requires-Dist: requests
